README.md
setup.py
csiot/__init__.py
csiot/api.py
csiot/config.py
csiot/message.py
csiot/service.py
csiot/util.py
csiot.egg-info/PKG-INFO
csiot.egg-info/SOURCES.txt
csiot.egg-info/dependency_links.txt
csiot.egg-info/top_level.txt