Metadata-Version: 1.0
Name: csiot
Version: 1.2.8
Summary: CSIoT Python SDK
Home-page: https://codestruct.net
Author: Kevin Morris
Author-email: kevin.morris@codestruct.net
License: UNKNOWN
Platform: UNKNOWN
